swittch/__init__.py
swittch/client.py
swittch/utils.py
swittch-0.0.2.dist-info/LICENSE
swittch-0.0.2.dist-info/METADATA
swittch-0.0.2.dist-info/WHEEL
swittch-0.0.2.dist-info/top_level.txt
swittch-0.0.2.dist-info/RECORD
